shopperops/__init__.py
shopperops/functions.py
shopperops-0.0.2.dist-info/METADATA
shopperops-0.0.2.dist-info/WHEEL
shopperops-0.0.2.dist-info/licenses/LICENSE
shopperops-0.0.2.dist-info/RECORD
